[
  {
    "id": "a685981f-ba94-48e8-b05b-a62c88822559",
    "name": {
      "name": "Pork ribs with bbq sauce"
    },
    "ingredients": [
      "porc ribs",
      "ketchup",
      "soy sauce",
      "honey",
      "thyme"
    ]
  },
  {
    "id": "6b133299-39b7-4ea0-b845-ef6f72134aef",
    "name": {
      "name": "caramel pork"
    },
    "ingredients": [
      "porc",
      "honey",
      "soy sauce",
      "sesame seeds"
    ]
  },
  {
    "id": "01524741-5821-4bee-90d2-3ea16c483c6e",
    "name": {
      "name": "caramel pork bis"
    },
    "ingredients": [
      "filet mignon",
      "spices",
      "sugar",
      "onion",
      "chicken stock",
      "ginger",
      "soy sauce"
    ]
  },
  {
    "id": "b005e302-c2cd-4188-8783-a0ce935d467e",
    "name": {
      "name": "Pineapple pork chops"
    },
    "ingredients": [
      "pineapple",
      "brown sugar",
      "soy sauce",
      "garlic powder",
      "pork chops"
    ]
  },
  {
    "id": "2a8a068c-cc46-4385-bd7e-43797adc9da6",
    "name": {
      "name": "Filet mignon of pork with apples and plums"
    },
    "ingredients": [
      "shallots",
      "quetsches",
      "olive oil",
      "filet mignon",
      "rosemary",
      "orange",
      "vinegar",
      "apple"
    ]
  },
  {
    "id": "71f46308-4f9c-40e5-83e7-f0d07e4dd0b8",
    "name": {
      "name": "Pork roast with soft onions"
    },
    "ingredients": [
      "butter",
      "olive oil",
      "sugar",
      "roast porc",
      "onion",
      "cinamon",
      "thyme",
      "laurel"
    ]
  },
  {
    "id": "f5e5b2a8-5faa-49a6-9139-4a84428b49a1",
    "name": {
      "name": "Italian pork chops with sage"
    },
    "ingredients": [
      "potatoes",
      "pork chops",
      "sage",
      "garlic",
      "prosciutto",
      "butter",
      "apricot",
      "olive oil",
      "flour",
      "pancetta"
    ]
  },
  {
    "id": "93304bf3-0190-462e-b9d7-c9eef9fafdc2",
    "name": {
      "name": "Pork with pineapple"
    },
    "ingredients": [
      "porc roast",
      "pineapple",
      "peanut oil",
      "garlic",
      "ginger",
      "soy sauce",
      "powdered pepper",
      "honey"
    ]
  },
  {
    "id": "1e182ad2-25a9-40d8-8946-e7c72015921f",
    "name": {
      "name": "Pork with porto and mushrooms"
    },
    "ingredients": [
      "porc",
      "olive oil",
      "mushrooms",
      "beef stock",
      "porto",
      "worcestershire sauce"
    ]
  },
  {
    "id": "9d2ce1ed-b336-4014-8d08-38716a115378",
    "name": {
      "name": "Pork chops with vinegar"
    },
    "ingredients": [
      "shallots",
      "olive oil",
      "porc",
      "vinegar",
      "garlic",
      "thyme"
    ]
  },
  {
    "id": "94321fd3-6292-4556-ae20-8c503bd20759",
    "name": {
      "name": "Filet mignon de porc with ham and veggies"
    },
    "ingredients": [
      "porc roast",
      "ham",
      "mustard",
      "onion",
      "beans",
      "green beans",
      "snow peas"
    ]
  },
  {
    "id": "f0049ab1-cc6b-48f1-a665-b2f06e5610a0",
    "name": {
      "name": "Pork chunks with spices"
    },
    "ingredients": [
      "onion",
      "porc",
      "olive oil",
      "veal",
      "spices"
    ]
  },
  {
    "id": "89858e38-e893-442d-9fef-0a30dc36fb4d",
    "name": {
      "name": "Pork with apricots"
    },
    "ingredients": [
      "porc",
      "olive oil",
      "onion",
      "apricots",
      "soy sauce",
      "honey",
      "parsley"
    ]
  },
  {
    "id": "bfd1348d-a413-4e5f-bf0c-c211cdc725c6",
    "name": {
      "name": "Nordic pork"
    },
    "ingredients": [
      "lemon",
      "rosemary",
      "thyme",
      "garlic",
      "pork"
    ]
  },
  {
    "id": "ff6bcbb9-d520-4a61-a1a0-c30c511a032a",
    "name": {
      "name": "crispy pork"
    },
    "ingredients": [
      "porc",
      "flour",
      "egg",
      "bread crumbs",
      "dill",
      "paprika",
      "vegetable oil",
      "celeriac",
      "mayonnaise",
      "mustard",
      "cream",
      "parsley",
      "lemon",
      "cress"
    ]
  },
  {
    "id": "81c51d02-e994-46f2-9afa-233935eb248e",
    "name": {
      "name": "Filet mighon of pork with pastry and cheese"
    },
    "ingredients": [
      "olive oil",
      "filet mignon",
      "egg",
      "cheddar",
      "vegetables",
      "butter",
      "stock",
      "dough"
    ]
  },
  {
    "id": "46e6bf54-eae8-44c9-8cbb-14ab0a156241",
    "name": {
      "name": "Vietnamese caramel pork"
    },
    "ingredients": [
      "filet mignoc",
      "soy sauce",
      "thai basil",
      "ginger",
      "lime",
      "hot pepper",
      "brown sugar",
      "vegetable oil"
    ]
  },
  {
    "id": "07fc3daf-3357-4162-ac54-08b709bb5f50",
    "name": {
      "name": "Vietnamese sweet and sour pork"
    },
    "ingredients": [
      "pork",
      "garlic",
      "shallots",
      "ginger",
      "brown sugar",
      "soy sauce",
      "chicken stock",
      "lime",
      "coriander"
    ]
  },
  {
    "id": "f50b71db-4fc3-440e-8ded-f44d18ed96ca",
    "name": {
      "name": "pulled pork sandwich"
    },
    "ingredients": [
      "onion powder",
      "garlic powder",
      "cumin",
      "paprika",
      "brown sugar",
      "porc",
      "apple juice",
      "burger buns",
      "coleslaw",
      "tomatoes"
    ]
  }
]
